source_google_analytics_v4/__init__.py
source_google_analytics_v4/custom_reports_validator.py
source_google_analytics_v4/defaults/default_reports.json
source_google_analytics_v4/run.py
source_google_analytics_v4/source.py
source_google_analytics_v4/spec.json
airbyte_source_google_analytics_v4-0.4.19.dist-info/METADATA
airbyte_source_google_analytics_v4-0.4.19.dist-info/WHEEL
airbyte_source_google_analytics_v4-0.4.19.dist-info/entry_points.txt
airbyte_source_google_analytics_v4-0.4.19.dist-info/RECORD
