Metadata-Version: 2.1
Name: airbyte-source-google-analytics-v4
Version: 0.4.19
Summary: Source implementation for Google Analytics V4.
Home-page: https://airbyte.com
License: Elv2
Author: Airbyte
Author-email: contact@airbyte.io
Requires-Python: >=3.9,<3.12
Classifier: License :: Other/Proprietary License
Classifier: Programming Language :: Python :: 3
Classifier: Programming Language :: Python :: 3.9
Classifier: Programming Language :: Python :: 3.10
Classifier: Programming Language :: Python :: 3.11
Requires-Dist: PyJWT (==2.8.0)
Requires-Dist: airbyte-cdk (>=0,<1)
Requires-Dist: cryptography (==41.0.4)
Requires-Dist: requests (==2.31.0)
Project-URL: Documentation, https://docs.airbyte.com/integrations/sources/google-analytics-v4
Project-URL: Repository, https://github.com/airbytehq/airbyte
